{
  "stats": {
    "suites": 1,
    "tests": 3,
    "passes": 3,
    "pending": 0,
    "failures": 0,
    "start": "2021-12-14T20:37:32.247Z",
    "end": "2021-12-14T20:37:32.583Z",
    "duration": 316,
    "testsRegistered": 3,
    "passPercent": 100,
    "pendingPercent": 0,
    "other": 0,
    "hasOther": false,
    "skipped": 0,
    "hasSkipped": false
  },
  "results": [
    {
      "uuid": "0a402e22-e2bb-4ae6-a1b8-ce76db6eaf42",
      "title": "",
      "fullFile": "cypress\\integration\\jsTaskParseListDOM.spec.js",
      "file": "cypress\\integration\\jsTaskParseListDOM.spec.js",
      "beforeHooks": [],
      "afterHooks": [],
      "tests": [],
      "suites": [
        {
          "uuid": "fb00bef5-ae8c-4362-ab03-61d81645402c",
          "title": "Parse list app ",
          "fullFile": "",
          "file": "",
          "beforeHooks": [],
          "afterHooks": [],
          "tests": [
            {
              "title": "should render list",
              "fullTitle": "Parse list app  should render list",
              "timedOut": null,
              "duration": 172,
              "state": "passed",
              "speed": "slow",
              "pass": true,
              "fail": false,
              "pending": false,
              "context": null,
              "code": "cy.get('ul');",
              "err": {},
              "uuid": "2edb2b1f-ca80-4905-bca8-f928d3f2a0ba",
              "parentUUID": "fb00bef5-ae8c-4362-ab03-61d81645402c",
              "isHook": false,
              "skipped": false
            },
            {
              "title": "should have 11 items",
              "fullTitle": "Parse list app  should have 11 items",
              "timedOut": null,
              "duration": 77,
              "state": "passed",
              "speed": "slow",
              "pass": true,
              "fail": false,
              "pending": false,
              "context": null,
              "code": "cy.get('ul > li').should('have.length', 11);",
              "err": {},
              "uuid": "ca0aaeae-354f-4767-9b81-f5fd81662b35",
              "parentUUID": "fb00bef5-ae8c-4362-ab03-61d81645402c",
              "isHook": false,
              "skipped": false
            },
            {
              "title": "should be sorted by salary DSC",
              "fullTitle": "Parse list app  should be sorted by salary DSC",
              "timedOut": null,
              "duration": 67,
              "state": "passed",
              "speed": "medium",
              "pass": true,
              "fail": false,
              "pending": false,
              "context": null,
              "code": "cy.get('ul > li').then(function ($ul) {\n  var list = (0, _toConsumableArray2.default)($ul).map(function (row) {\n    return row.dataset.salary.replace('$', '').replace(',', '');\n  });\n  var counter = 0;\n  for (var i = 0; i < list.length; i++) {\n    if (Number(list[i + 1]) <= Number(list[i])) {\n      counter += 1;\n    }\n  }\n  expect(counter).to.equal(list.length - 1);\n});",
              "err": {},
              "uuid": "8a42b096-782e-435a-931a-320587aff203",
              "parentUUID": "fb00bef5-ae8c-4362-ab03-61d81645402c",
              "isHook": false,
              "skipped": false
            }
          ],
          "suites": [],
          "passes": [
            "2edb2b1f-ca80-4905-bca8-f928d3f2a0ba",
            "ca0aaeae-354f-4767-9b81-f5fd81662b35",
            "8a42b096-782e-435a-931a-320587aff203"
          ],
          "failures": [],
          "pending": [],
          "skipped": [],
          "duration": 316,
          "root": false,
          "rootEmpty": false,
          "_timeout": 2000
        }
      ],
      "passes": [],
      "failures": [],
      "pending": [],
      "skipped": [],
      "duration": 0,
      "root": true,
      "rootEmpty": true,
      "_timeout": 2000
    }
  ],
  "meta": {
    "mocha": {
      "version": "7.0.1"
    },
    "mochawesome": {
      "options": {
        "quiet": false,
        "reportFilename": "mochawesome",
        "saveHtml": false,
        "saveJson": true,
        "consoleReporter": "spec",
        "useInlineDiffs": false,
        "code": true
      },
      "version": "6.2.1"
    },
    "marge": {
      "options": {
        "reportDir": "raw_reports",
        "overwrite": false,
        "html": false,
        "json": true
      },
      "version": "5.1.0"
    }
  }
}